{
  "source_tvdb_id": 70851,
  "target_tvdb_id": 131,
  "source_imdb_id": "nm0085312",
  "target_imdb_id": "nm0350453",
  "min_moves_to_solve": 3,
  "source_birthday": false,
  "best_solution": [
    {
      "type": "Actor",
      "imdb_id": "nm0085312",
      "tvdb_id": 70851,
      "name": "Jack Black",
      "image_url": "https://image.tmdb.org/t/p/w500/rtCx0fiYxJVhzXXdwZE2XRTfIKE.jpg"
    },
    {
      "type": "Film",
      "imdb_id": "tt0942385",
      "votes": 427941,
      "rating": 7.1,
      "name": "Tropic Thunder",
      "tvdb_id": 7446,
      "image_url": "https://image.tmdb.org/t/p/w500/zAurB9mNxfYRoVrVjAJJwGV3sPg.jpg"
    },
    {
      "type": "Actor",
      "imdb_id": "nm0000375",
      "tvdb_id": 3223,
      "name": "Robert Downey Jr.",
      "image_url": "https://image.tmdb.org/t/p/w500/im9SAqJPZKEbVZGmjXuLI4O7RvM.jpg"
    },
    {
      "type": "Film",
      "imdb_id": "tt0443706",
      "votes": 559085,
      "rating": 7.7,
      "name": "Zodiac",
      "tvdb_id": 1949,
      "image_url": "https://image.tmdb.org/t/p/w500/hQhcbb8JvPFPkhaWUsG545d9LRD.jpg"
    },
    {
      "type": "Actor",
      "imdb_id": "nm0350453",
      "tvdb_id": 131,
      "name": "Jake Gyllenhaal",
      "image_url": "https://image.tmdb.org/t/p/w500/rJdYHYNhlcOBwbPvDZVvt1xw7bi.jpg"
    }
  ]
}