{
  "source_tvdb_id": 57755,
  "target_tvdb_id": 3129,
  "source_imdb_id": "nm0000437",
  "target_imdb_id": "nm0000619",
  "min_moves_to_solve": 3,
  "source_birthday": false,
  "best_solution": [
    {
      "type": "Actor",
      "imdb_id": "nm0000437",
      "tvdb_id": 57755,
      "name": "Woody Harrelson",
      "image_url": "https://image.tmdb.org/t/p/w500/igxYDQBbTEdAqaJxaW6ffqswmUU.jpg"
    },
    {
      "type": "Film",
      "imdb_id": "tt1951264",
      "votes": 681269,
      "rating": 7.5,
      "name": "The Hunger Games: Catching Fire",
      "tvdb_id": 101299,
      "image_url": "https://image.tmdb.org/t/p/w500/vrQHDXjVmbYzadOXQ0UaObunoy2.jpg"
    },
    {
      "type": "Actor",
      "imdb_id": "nm0001625",
      "tvdb_id": 99,
      "name": "Amanda Plummer",
      "image_url": "https://image.tmdb.org/t/p/w500/joHGUtEmXzJkH6ogEliiUKT9MNa.jpg"
    },
    {
      "type": "Film",
      "imdb_id": "tt0110912",
      "votes": 2101050,
      "rating": 8.9,
      "name": "Pulp Fiction",
      "tvdb_id": 680,
      "image_url": "https://image.tmdb.org/t/p/w500/d5iIlFn5s0ImszYzBPb8JPIfbXD.jpg"
    },
    {
      "type": "Actor",
      "imdb_id": "nm0000619",
      "tvdb_id": 3129,
      "name": "Tim Roth",
      "image_url": "https://image.tmdb.org/t/p/w500/qSizF2i9gz6c6DbAC5RoIq8sVqX.jpg"
    }
  ]
}