{
  "source_tvdb_id": 2440,
  "target_tvdb_id": 11701,
  "source_imdb_id": "nm0631490",
  "target_imdb_id": "nm0001401",
  "min_moves_to_solve": 3,
  "source_birthday": false,
  "best_solution": [
    {
      "type": "Actor",
      "imdb_id": "nm0631490",
      "tvdb_id": 2440,
      "name": "Bill Nighy",
      "image_url": "https://image.tmdb.org/t/p/w500/ixFI2YCGNGJfwlpI8iyhvVZRg8C.jpg"
    },
    {
      "type": "Film",
      "imdb_id": "tt0383574",
      "votes": 734303,
      "rating": 7.3,
      "name": "Pirates of the Caribbean: Dead Man's Chest",
      "tvdb_id": 58,
      "image_url": "https://image.tmdb.org/t/p/w500/uXEqmloGyP7UXAiphJUu2v2pcuE.jpg"
    },
    {
      "type": "Actor",
      "imdb_id": "nm0000136",
      "tvdb_id": 85,
      "name": "Johnny Depp",
      "image_url": "https://image.tmdb.org/t/p/w500/e0G2pxUxuVb42bYmn4C1vdDlsLc.jpg"
    },
    {
      "type": "Film",
      "imdb_id": "tt1243957",
      "votes": 248399,
      "rating": 6.0,
      "name": "The Tourist",
      "tvdb_id": 37710,
      "image_url": "https://image.tmdb.org/t/p/w500/oXe1nw4HcS32YVpvxwsWEVdvEXA.jpg"
    },
    {
      "type": "Actor",
      "imdb_id": "nm0001401",
      "tvdb_id": 11701,
      "name": "Angelina Jolie",
      "image_url": "https://image.tmdb.org/t/p/w500/k3W1XXddDOH2zibPkNotIh5amHo.jpg"
    }
  ]
}