{
  "source_tvdb_id": 10980,
  "target_tvdb_id": 27578,
  "source_imdb_id": "nm0705356",
  "target_imdb_id": "nm0680983",
  "min_moves_to_solve": 3,
  "source_birthday": true,
  "best_solution": [
    {
      "type": "Actor",
      "imdb_id": "nm0705356",
      "tvdb_id": 10980,
      "name": "Daniel Radcliffe",
      "image_url": "https://image.tmdb.org/t/p/w500/iPg0J9UzAlPj1fLEJNllpW9IhGe.jpg"
    },
    {
      "type": "Film",
      "imdb_id": "tt3110958",
      "votes": 301677,
      "rating": 6.4,
      "name": "Now You See Me 2",
      "tvdb_id": 291805,
      "image_url": "https://image.tmdb.org/t/p/w500/A81kDB6a1K86YLlcOtZB27jriJh.jpg"
    },
    {
      "type": "Actor",
      "imdb_id": "nm0000323",
      "tvdb_id": 3895,
      "name": "Michael Caine",
      "image_url": "https://image.tmdb.org/t/p/w500/hZruclwEPCKw3e83rnFSIH5sRFZ.jpg"
    },
    {
      "type": "Film",
      "imdb_id": "tt1375666",
      "votes": 2403153,
      "rating": 8.8,
      "name": "Inception",
      "tvdb_id": 27205,
      "image_url": "https://image.tmdb.org/t/p/w500/edv5CZvWj09upOsy2Y6IwDhK8bt.jpg"
    },
    {
      "type": "Actor",
      "imdb_id": "nm0680983",
      "tvdb_id": 27578,
      "name": "Elliot Page",
      "image_url": "https://image.tmdb.org/t/p/w500/3gVm1jSZERNTCKqtgXRC0J3COtn.jpg"
    }
  ]
}