{
  "source_tvdb_id": 4783,
  "target_tvdb_id": 3087,
  "source_imdb_id": "nm0000554",
  "target_imdb_id": "nm0000380",
  "min_moves_to_solve": 3,
  "source_birthday": true,
  "best_solution": [
    {
      "type": "Actor",
      "imdb_id": "nm0000554",
      "tvdb_id": 4783,
      "name": "Sam Neill",
      "image_url": "https://image.tmdb.org/t/p/w500/8A6UifLxsv9Q45plOMGXgVHOl9I.jpg"
    },
    {
      "type": "Film",
      "imdb_id": "tt0163025",
      "votes": 329537,
      "rating": 5.9,
      "name": "Jurassic Park III",
      "tvdb_id": 331,
      "image_url": "https://image.tmdb.org/t/p/w500/oQXj4NUfS3r3gHXtDOzcJgj1lLc.jpg"
    },
    {
      "type": "Actor",
      "imdb_id": "nm0000495",
      "tvdb_id": 4939,
      "name": "T\u00e9a Leoni",
      "image_url": "https://image.tmdb.org/t/p/w500/vWijsKTlNs9bgKdUVgsr2w4msGo.jpg"
    },
    {
      "type": "Film",
      "imdb_id": "tt0120647",
      "votes": 182767,
      "rating": 6.2,
      "name": "Deep Impact",
      "tvdb_id": 8656,
      "image_url": "https://image.tmdb.org/t/p/w500/a3vQS7JKqlOb3MdVJHuTCP9s7Mg.jpg"
    },
    {
      "type": "Actor",
      "imdb_id": "nm0000380",
      "tvdb_id": 3087,
      "name": "Robert Duvall",
      "image_url": "https://image.tmdb.org/t/p/w500/3tcKxC5Sc3DJ6XPDKKC2EAomEWn.jpg"
    }
  ]
}