{
  "source_tvdb_id": 27319,
  "target_tvdb_id": 4783,
  "source_imdb_id": "nm0910607",
  "target_imdb_id": "nm0000554",
  "min_moves_to_solve": 3,
  "source_birthday": false,
  "best_solution": [
    {
      "type": "Actor",
      "imdb_id": "nm0910607",
      "tvdb_id": 27319,
      "name": "Christoph Waltz"
    },
    {
      "type": "Film",
      "imdb_id": "tt1853728",
      "votes": 1592500,
      "rating": 8.4,
      "name": "Django Unchained",
      "tvdb_id": 68718
    },
    {
      "type": "Actor",
      "imdb_id": "nm0000168",
      "tvdb_id": 2231,
      "name": "Samuel L. Jackson"
    },
    {
      "type": "Film",
      "imdb_id": "tt0107290",
      "votes": 1010271,
      "rating": 8.2,
      "name": "Jurassic Park",
      "tvdb_id": 329
    },
    {
      "type": "Actor",
      "imdb_id": "nm0000554",
      "tvdb_id": 4783,
      "name": "Sam Neill"
    }
  ]
}