{
  "source_tvdb_id": 1328,
  "target_tvdb_id": 2440,
  "source_imdb_id": "nm0000276",
  "target_imdb_id": "nm0631490",
  "min_moves_to_solve": 3,
  "source_birthday": true,
  "best_solution": [
    {
      "type": "Actor",
      "imdb_id": "nm0000276",
      "tvdb_id": 1328,
      "name": "Sean Astin",
      "image_url": "https://image.tmdb.org/t/p/w500/5oJzy6Ra0tuMEV7mfxjtqye5qUX.jpg"
    },
    {
      "type": "Film",
      "imdb_id": "tt0167261",
      "votes": 1697780,
      "rating": 8.8,
      "name": "The Lord of the Rings: The Two Towers",
      "tvdb_id": 121,
      "image_url": "https://image.tmdb.org/t/p/w500/5VTN0pR8gcqV3EPUHHfMGnJYN9L.jpg"
    },
    {
      "type": "Actor",
      "imdb_id": "nm0089217",
      "tvdb_id": 114,
      "name": "Orlando Bloom",
      "image_url": "https://image.tmdb.org/t/p/w500/lwQoA0qJTCZ6l2FH6PjmhRQjiaB.jpg"
    },
    {
      "type": "Film",
      "imdb_id": "tt0383574",
      "votes": 734303,
      "rating": 7.3,
      "name": "Pirates of the Caribbean: Dead Man's Chest",
      "tvdb_id": 58,
      "image_url": "https://image.tmdb.org/t/p/w500/uXEqmloGyP7UXAiphJUu2v2pcuE.jpg"
    },
    {
      "type": "Actor",
      "imdb_id": "nm0631490",
      "tvdb_id": 2440,
      "name": "Bill Nighy",
      "image_url": "https://image.tmdb.org/t/p/w500/ixFI2YCGNGJfwlpI8iyhvVZRg8C.jpg"
    }
  ]
}